TileGenerator/__init__.py
TileGenerator/_nbdev.py
TileGenerator/core.py
TileGenerator/tile_generator.py
TileGenerator-0.0.3.dist-info/LICENSE
TileGenerator-0.0.3.dist-info/METADATA
TileGenerator-0.0.3.dist-info/WHEEL
TileGenerator-0.0.3.dist-info/entry_points.txt
TileGenerator-0.0.3.dist-info/top_level.txt
TileGenerator-0.0.3.dist-info/RECORD
